pypimonitor/__init__.py
pypimonitor/__main__.py
pypimonitor/cell/__init__.py
pypimonitor/cell/base.py
pypimonitor/cell/gitlab.py
pypimonitor/cell/pypi.py
pypimonitor/cell/readthedocs.py
pypimonitor/cell/shields.py
pypimonitor/cell/travis.py
pypimonitor-0.6.0.dist-info/AUTHORS
pypimonitor-0.6.0.dist-info/LICENSE
pypimonitor-0.6.0.dist-info/METADATA
pypimonitor-0.6.0.dist-info/WHEEL
pypimonitor-0.6.0.dist-info/entry_points.txt
pypimonitor-0.6.0.dist-info/top_level.txt
pypimonitor-0.6.0.dist-info/RECORD
