Metadata-Version: 2.1
Name: pypimonitor
Version: 0.6.0
Summary: An HTML dashboard to monitor your pypi projects.
Home-page: http://framagit.org/spalax/pypimonitor
Author: Louis Paternault
Author-email: spalax@gresille.org
License: AGPLv3 or any later version
Project-URL: Documentation, http://pypimonitor.readthedocs.io
Project-URL: Source, https://framagit.org/spalax/pypimonitor
Project-URL: Tracker, https://framagit.org/spalax/pypimonitor/issues
Keywords: pypi monitor statistics
Classifier: Development Status :: 5 - Production/Stable
Classifier: Intended Audience :: Developers
Classifier: License :: OSI Approved :: GNU Affero General Public License v3 or later (AGPLv3+)
Classifier: Programming Language :: Python :: 3 :: Only
Classifier: Programming Language :: Python :: 3.8
Classifier: Programming Language :: Python :: 3.9
Classifier: Programming Language :: Python :: 3.10
Classifier: Programming Language :: Python :: 3.11
Classifier: Programming Language :: Python :: 3.12
Classifier: Programming Language :: Python :: 3.13
Classifier: Topic :: Software Development :: Quality Assurance
Requires-Python: <4,>=3.8
License-File: LICENSE
License-File: AUTHORS
Requires-Dist: jinja2>=3
Requires-Dist: pyyaml
Requires-Dist: requests
